popbill/__init__.py
popbill/accountCheckService.py
popbill/base.py
popbill/bizInfoCheckService.py
popbill/cashbillService.py
popbill/closedownService.py
popbill/easyFinBankService.py
popbill/faxService.py
popbill/htCashbillService.py
popbill/htTaxinvoiceService.py
popbill/kakaoService.py
popbill/messageService.py
popbill/statementService.py
popbill/taxinvoiceService.py
popbill-1.63.0.dist-info/LICENSE.md
popbill-1.63.0.dist-info/METADATA
popbill-1.63.0.dist-info/WHEEL
popbill-1.63.0.dist-info/top_level.txt
popbill-1.63.0.dist-info/RECORD
