Metadata-Version: 2.1
Name: popbill
Version: 1.63.0
Summary: Popbill API SDK Library
Home-page: https://github.com/linkhub-sdk/Popbill.py
Author: LINKHUB DEV Team
Author-email: code@linkhubcorp.com
License: MIT
Download-URL: https://github.com/linkhub-sdk/Popbill.py/archive/1.63.0.tar.gz
Platform: Posix; MacOS X; Windows
Classifier: Development Status :: 5 - Production/Stable
Classifier: Intended Audience :: Developers
Classifier: License :: OSI Approved :: MIT License
Classifier: Operating System :: OS Independent
Classifier: Topic :: Internet
Classifier: Programming Language :: Python :: 2
Classifier: Programming Language :: Python :: 2.6
Classifier: Programming Language :: Python :: 2.7
Classifier: Programming Language :: Python :: 3
Classifier: Programming Language :: Python :: 3.3
Classifier: Programming Language :: Python :: 3.4
Classifier: Programming Language :: Python :: 3.5
Classifier: Programming Language :: Python :: 3.6
Classifier: Programming Language :: Python :: 3.7
Classifier: Programming Language :: Python :: 3.8
Classifier: Programming Language :: Python :: 3.9
Classifier: Programming Language :: Python :: 3.10
Requires-Dist: linkhub
